casey/__init__.py
casey/py.typed
casey-1.2.0.dist-info/LICENSE
casey-1.2.0.dist-info/WHEEL
casey-1.2.0.dist-info/METADATA
casey-1.2.0.dist-info/RECORD
