Metadata-Version: 2.1
Name: casey
Version: 1.2.0
Summary: A simple library to support various naming conventions and convert strings from one to another
Home-page: https://github.com/marverix/casey
License: Apache-2.0
Keywords: naming conventions,camelCase,PascalCase,kebab-case,snake_case
Author: Marek Sierociński
Author-email: mareksierocinski@gmail.com
Requires-Python: >=3.6,<4.0
Classifier: License :: OSI Approved :: Apache Software License
Classifier: Programming Language :: Python :: 3
Classifier: Programming Language :: Python :: 3.10
Classifier: Programming Language :: Python :: 3.6
Classifier: Programming Language :: Python :: 3.7
Classifier: Programming Language :: Python :: 3.8
Classifier: Programming Language :: Python :: 3.9
Classifier: Topic :: Utilities
Project-URL: Repository, https://github.com/marverix/casey
